Workbook
Name Cloud_AWS: Regiones!$B$2:$B$28
Name Cloud_Azure: Regiones!$B$29:$B$60
Name Cloud_GCP: Regiones!$B$61:$B$90
Name AllClaves: Regiones!$G$2:$G$90
Name AllClouds: Listas!$A$2:$A$4
Name CL_PUBLIC_HOUR: Tarifas!$B$6
Name CL_PRIVATE_HOUR: Tarifas!$B$7
Name CL_XCLOUD_HOUR: Tarifas!$B$8
Name CL_XCLOUD_PREMIUM_HOUR: Tarifas!$B$9
Name CL_READ_GB: Tarifas!$B$10
Name CKU_HOUR: Tarifas!$B$14
Name KAFKA_IN_GB: Tarifas!$B$15
Name KAFKA_OUT_GB: Tarifas!$B$16
Name STORAGE_GB_MONTH: Tarifas!$B$17
Name CSP_PE_HOUR: Tarifas!$B$18
Name CSP_PE_GB: Tarifas!$B$19
Name HOURS_MONTH: Tarifas!$B$20
Name REPL_FACTOR: Tarifas!$B$21
Name CKU_IN_MBPS: Tarifas!$B$22
Name CKU_OUT_MBPS: Tarifas!$B$23
Name CKU_PARTITIONS: Tarifas!$B$24

Sheet Calculadora
A1: Calculadora Private Link · Confluent Cloud Dedicated
A2: Celdas amarillas = input. El resto son fórmulas. Cluster Linking $0.25 / $0.50 / $2.50 / $5.00 y $0.25/GB son oficiales. Dedicated CKU/ingress/egress/storage: editar en hoja Tarifas con `confluent billing price list`.
A4: Cluster A · source | E4: Cluster B · destination | I4: Estimado mensual USD
A5: Cloud | B5: Azure | E5: Cloud | F5: AWS | I5: Concepto | J5: USD / mes | K5: Cómo se calcula | L5: Bloque
A6: Region | B6: eastus2 | E6: Region | F6: us-east-1 | I6: CKU cluster A | J6: =$B$8*CKU_HOUR*$F$17*HOURS_MONTH | K6: =$B$8&" CKU × "&TEXT(CKU_HOUR*$F$17,"$0.00")&"/h × "&HOURS_MONTH&"h" | L6: Confluent
A7: Availability | B7: Multi-zone | E7: Availability | F7: Multi-zone | I7: CKU cluster B | J7: =$F$8*CKU_HOUR*$F$20*HOURS_MONTH | K7: =$F$8&" CKU × "&TEXT(CKU_HOUR*$F$20,"$0.00")&"/h × "&HOURS_MONTH&"h" | L7: Confluent
A8: CKU | B8: 2 | E8: CKU | F8: 2 | I8: Kafka ingress clientes A | J8: =$B$10*KAFKA_IN_GB*$F$17 | K8: =$B$10&" GB × "&TEXT(KAFKA_IN_GB*$F$17,"$0.00") | L8: Confluent
A9: VNets / VPCs cliente | B9: 1 | E9: VNets / VPCs cliente | F9: 1 | I9: Kafka ingress clientes B | J9: =$F$10*KAFKA_IN_GB*$F$20 | K9: =$F$10&" GB × "&TEXT(KAFKA_IN_GB*$F$20,"$0.00") | L9: Confluent
A10: Produce cliente (GB/mes) | B10: 400 | E10: Produce cliente (GB/mes) | F10: 0 | I10: Kafka egress clientes A | J10: =$B$11*KAFKA_OUT_GB*$F$17 | K10: =$B$11&" GB × "&TEXT(KAFKA_OUT_GB*$F$17,"$0.00") | L10: Confluent
A11: Consume cliente (GB/mes) | B11: 800 | E11: Consume cliente (GB/mes) | F11: 400 | I11: Kafka egress clientes B | J11: =$F$11*KAFKA_OUT_GB*$F$20 | K11: =$F$11&" GB × "&TEXT(KAFKA_OUT_GB*$F$20,"$0.00") | L11: Confluent
A12: Storage pre-RF (GB) | B12: 200 | E12: Storage pre-RF (GB) | F12: 200 | I12: Storage A (× RF) | J12: =$B$12*REPL_FACTOR*STORAGE_GB_MONTH | K12: =$B$12&" GB pre x "&REPL_FACTOR&" x "&TEXT(STORAGE_GB_MONTH,"$0.00") | L12: Confluent
I13: Storage B (× RF) | J13: =$F$12*REPL_FACTOR*STORAGE_GB_MONTH | K13: =$F$12&" GB pre x "&REPL_FACTOR&" x "&TEXT(STORAGE_GB_MONTH,"$0.00") | L13: Confluent
A14: Cluster Linking | E14: Diagnóstico (fórmulas) | I14: Cluster link hourly A | J14: =$F$25*$F$22*HOURS_MONTH | K14: =TEXT($F$25,"$0.00")&"/h × "&$F$22&" link(s) × "&HOURS_MONTH&"h" | L14: Confluent
A15: Direccion | B15: Unidirectional | E15: Premium A | F15: =IFERROR(INDEX(Regiones!$D$2:$D$90,MATCH($B$5&"|"&$B$6,Regiones!$G$2:$G$90,0)),"NO") | I15: Cluster link hourly B | J15: =$F$26*$F$22*HOURS_MONTH | K15: =TEXT($F$26,"$0.00")&"/h × "&$F$22&" link(s) × "&HOURS_MONTH&"h" | L15: Confluent
A16: Mirror A → B (GB/mes) | B16: 500 | E16: Jio A (sin PL) | F16: =IFERROR(INDEX(Regiones!$E$2:$E$90,MATCH($B$5&"|"&$B$6,Regiones!$G$2:$G$90,0)),"NO") | I16: ClusterLinkingRead A→B | J16: =$F$23*CL_READ_GB*$F$17 | K16: =$F$23&" GB × "&TEXT(CL_READ_GB,"$0.00")&" × "&$F$17 | L16: Confluent
A17: Mirror B → A (GB/mes) | B17: 0 | E17: Multiplier A | F17: =IFERROR(INDEX(Regiones!$F$2:$F$90,MATCH($B$5&"|"&$B$6,Regiones!$G$2:$G$90,0)),1) | I17: ClusterLinkingWrite A→B | J17: =$F$23*KAFKA_IN_GB*$F$20 | K17: =$F$23&" GB × dest KafkaNetworkWrite" | L17: Confluent
E18: Premium B | F18: =IFERROR(INDEX(Regiones!$D$2:$D$90,MATCH($F$5&"|"&$F$6,Regiones!$G$2:$G$90,0)),"NO") | I18: ClusterLinkingRead B→A | J18: =$F$24*CL_READ_GB*$F$20 | K18: =$F$24&" GB × "&TEXT(CL_READ_GB,"$0.00")&" × "&$F$20 | L18: Confluent
A19: Cómo usar | E19: Jio B (sin PL) | F19: =IFERROR(INDEX(Regiones!$E$2:$E$90,MATCH($F$5&"|"&$F$6,Regiones!$G$2:$G$90,0)),"NO") | I19: ClusterLinkingWrite B→A | J19: =$F$24*KAFKA_IN_GB*$F$17 | K19: =$F$24&" GB × dest KafkaNetworkWrite" | L19: Confluent
A20: 1. Elige Cloud y Region de A y B (el dropdown de Region depende del Cloud). 2. Multi-zone Dedicated exige mínimo 2 CKU y 3 endpoints (Azure/GCP) o 1 VPCE en 3 AZ (AWS). 3. Dirección: Unidirectional = 1 link; Bidirectional = 2; None = 0. El objeto se cobra aunque GB = 0. 4. Cross-cloud + ambos private: hourly $2.50, o $5.00 si Premium (hoja Regiones). 5. Intra-cloud private: $0.50/h × multiplier de esa región. 6. ClusterLinkingWrite = Kafka ingress del destination. No se cobra Kafka ingress extra. 7. ClusterLinkingRead = $0.25/GB (oficial). Confluent paga el egress del cloud provider. 8. Private-to-private Dedicated exige la MISMA Confluent Cloud Organization. 9. Un cluster existente NO se convierte a Private Link. Jio no tiene PL. 10. Schema Registry, CLI y provisioning de ksqlDB siguen necesitando Internet. 11. Pega tus tarifas Dedicated reales en la hoja Tarifas. 12. GB = GiB (2^30). Billing en UTC. | E20: Multiplier B | F20: =IFERROR(INDEX(Regiones!$F$2:$F$90,MATCH($F$5&"|"&$F$6,Regiones!$G$2:$G$90,0)),1) | I20: CSP endpoints A | J20: =$F$29*CSP_PE_HOUR*HOURS_MONTH+($B$10+$B$11)*CSP_PE_GB | K20: =$F$29&" unidades + "&($B$10+$B$11)&" GB cliente" | L20: CSP
E21: Cross-cloud | F21: =$B$5<>$F$5 | I21: CSP endpoints B | J21: =$F$30*CSP_PE_HOUR*HOURS_MONTH+($F$10+$F$11)*CSP_PE_GB | K21: =$F$30&" unidades + "&($F$10+$F$11)&" GB cliente" | L21: CSP
E22: Links | F22: =IF(OR($B$15="None",$B$15="Sin Cluster Linking"),0,IF($B$15="Bidirectional",2,1)) | I22: Subtotal Confluent | J22: =SUMIF($L$6:$L$21,"Confluent",$J$6:$J$21)
E23: GB A→B efectivo | F23: =IF(OR($B$15="None",$B$15="Sin Cluster Linking"),0,$B$16) | I23: Subtotal CSP | J23: =SUMIF($L$6:$L$21,"CSP",$J$6:$J$21)
E24: GB B→A efectivo | F24: =IF($B$15="Bidirectional",$B$17,0) | I24: TOTAL USD / mes | J24: =J22+J23 | K24: Confluent + endpoints del cloud provider
E25: Hourly A | F25: =IF($F$22=0,0,IF($F$21,IF($F$15="SI",CL_XCLOUD_PREMIUM_HOUR,CL_XCLOUD_HOUR),CL_PRIVATE_HOUR*$F$17))
E26: Hourly B | F26: =IF($F$22=0,0,IF($F$21,IF($F$18="SI",CL_XCLOUD_PREMIUM_HOUR,CL_XCLOUD_HOUR),CL_PRIVATE_HOUR*$F$20)) | I26: Private Link a provisionar
E27: AZ por red A | F27: =IF($B$7="Single-zone",1,3) | I27: A | J27: =$F$31&" x "&$F$33
E28: AZ por red B | F28: =IF($F$7="Single-zone",1,3) | I28: B | J28: =$F$32&" x "&$F$34
E29: Unidades CSP A | F29: =$B$9*$F$27 | I29: DNS por cluster | J29: =IF($B$7="Single-zone","* + 1 zonal (A records)","* + 3 zonales (A/CNAME). No hardcodear brokers.")
E30: Unidades CSP B | F30: =$F$9*$F$28 | I30: CKU A / B vs guía | J30: =$B$8&" / "&$F$8&" (sugerido "&$F$38&" / "&$F$39&")"
E31: Endpoints a crear A | F31: =IF($B$5="AWS",$B$9,$B$9*$F$27)
E32: Endpoints a crear B | F32: =IF($F$5="AWS",$F$9,$F$9*$F$28) | I32: Gráfico
E33: Tipo endpoint A | F33: =IF($B$5="AWS","VPC endpoint (1 × N AZ)",IF($B$5="Azure","Private Endpoints","PSC endpoints")) | I33: CKU | J33: =J6+J7
E34: Tipo endpoint B | F34: =IF($F$5="AWS","VPC endpoint (1 × N AZ)",IF($F$5="Azure","Private Endpoints","PSC endpoints")) | I34: Kafka in/out + storage | J34: =SUM(J8:J13)
E35: Región válida A | F35: =IF(COUNTIFS(Regiones!$A$2:$A$90,$B$5,Regiones!$B$2:$B$90,$B$6)=1,"OK","Region no coincide con cloud") | I35: Cluster Linking | J35: =SUM(J14:J19)
E36: Región válida B | F36: =IF(COUNTIFS(Regiones!$A$2:$A$90,$F$5,Regiones!$B$2:$B$90,$F$6)=1,"OK","Region no coincide con cloud") | I36: CSP Private Link | J36: =J23
E37: Mismo Organization | F37: OBLIGATORIO si ambos son private Dedicated
E38: CKU sugerido A | F38: =MAX(IF($B$7="Multi-zone",2,1),ROUNDUP(MAX((($B$10+$F$24)*1024)/(HOURS_MONTH*3600)/CKU_IN_MBPS,(($B$11+$F$23)*1024)/(HOURS_MONTH*3600)/CKU_OUT_MBPS),0))
E39: CKU sugerido B | F39: =MAX(IF($F$7="Multi-zone",2,1),ROUNDUP(MAX((($F$10+$F$23)*1024)/(HOURS_MONTH*3600)/CKU_IN_MBPS,(($F$11+$F$24)*1024)/(HOURS_MONTH*3600)/CKU_OUT_MBPS),0))
E40: Alerta CKU / Jio / PL | F40: =IF(OR($F$16="SI",$F$19="SI"),"Jio: no Private Link. ","")&IF(OR($B$8<$F$38,$F$8<$F$39),"CKU por debajo de la guia. ","")&IF(OR(AND($B$7="Multi-zone",$B$8<2),AND($F$7="Multi-zone",$F$8<2)),"Multi-zone exige 2 CKU. ","")&IF($F$21,"Cross-cloud private Cluster Linking. ","Intra-cloud private. ")&IF(OR($F$15="SI",$F$18="SI"),"Premium region $5.00/h. ","")&IF($F$22=2,"Bidirectional = 2 links. ","")&IF(OR($F$35<>"OK",$F$36<>"OK"),"Region no coincide con cloud.","")

Sheet Tarifas
A1: Tarifas y constantes
A2: Amarillo = editable. Cluster Linking hourly/GB son list prices oficiales. Dedicated CKU/ingress/egress/storage no son list price público.
A4: Cluster Linking (oficial, Billing Dimensions)
A5: Clave | B5: USD | C5: Nota
A6: CL_PUBLIC_HOUR | B6: 0.25 | C6: USD/h por cluster si el endpoint es internet
A7: CL_PRIVATE_HOUR | B7: 0.5 | C7: USD/h por cluster intra-cloud private
A8: CL_XCLOUD_HOUR | B8: 2.5 | C8: USD/h por cluster cross-cloud private
A9: CL_XCLOUD_PREMIUM_HOUR | B9: 5 | C9: USD/h si esa región es Premium (docs Regions)
A10: CL_READ_GB | B10: 0.25 | C10: USD/GB ClusterLinkingRead. Confluent paga egress CSP
A12: Dedicated (editable — no es list price público)
A13: Clave | B13: USD | C13: Nota
A14: CKU_HOUR | B14: 1.5 | C14: USD/CKU-hora base. Sacar de: confluent billing price list
A15: KAFKA_IN_GB | B15: 0.1 | C15: KafkaNetworkWrite USD/GB base
A16: KAFKA_OUT_GB | B16: 0.05 | C16: KafkaNetworkRead USD/GB base
A17: STORAGE_GB_MONTH | B17: 0.08 | C17: USD/GB-mes post-replication
A18: CSP_PE_HOUR | B18: 0.01 | C18: Azure PE / AWS VPCE-AZ / GCP PSC USD/hora (list US)
A19: CSP_PE_GB | B19: 0.01 | C19: CSP data processed USD/GB (list US)
A20: HOURS_MONTH | B20: 730 | C20: Horas / mes (24×365/12)
A21: REPL_FACTOR | B21: 3 | C21: Replication factor Dedicated. Storage ≈ 3x
A22: CKU_IN_MBPS | B22: 60 | C22: Ingress MBps por CKU (docs cluster types)
A23: CKU_OUT_MBPS | B23: 180 | C23: Egress MBps por CKU
A24: CKU_PARTITIONS | B24: 4500 | C24: Partitions pre-replication por CKU
A26: Tope CKU Dedicated por cloud
A27: AWS | B27: 252
A28: Azure | B28: 100
A29: GCP | B29: 152
A31: Fuentes oficiales
A32: https://docs.confluent.io/cloud/current/billing/billing-dimensions.html
A33: https://docs.confluent.io/cloud/current/multi-cloud/cluster-linking/private-networking.html
A34: https://docs.confluent.io/cloud/current/get-started/regions.html
A35: https://docs.confluent.io/cloud/current/networking/private-links/azure-privatelink.html
A36: https://docs.confluent.io/cloud/current/networking/private-links/aws-privatelink.html
A37: https://docs.confluent.io/cloud/current/networking/private-links/gcp-private-service-connect.html
A38: https://docs.confluent.io/cloud/current/clusters/cluster-types.html

Sheet Regiones
A1: Cloud | B1: Region | C1: Ubicacion | D1: Premium_cross_cloud | E1: Jio_sin_PL | F1: Multiplier | G1: Clave
A2: AWS | B2: us-east-1 | C2: N. Virginia | D2: NO | E2: NO | F2: 1 | G2: AWS|us-east-1
A3: AWS | B3: us-east-2 | C3: Ohio | D3: NO | E3: NO | F3: 1 | G3: AWS|us-east-2
A4: AWS | B4: us-west-2 | C4: Oregon | D4: NO | E4: NO | F4: 1 | G4: AWS|us-west-2
A5: AWS | B5: ca-central-1 | C5: Canada Central | D5: NO | E5: NO | F5: 1 | G5: AWS|ca-central-1
A6: AWS | B6: ca-west-1 | C6: Calgary | D6: NO | E6: NO | F6: 1 | G6: AWS|ca-west-1
A7: AWS | B7: sa-east-1 | C7: São Paulo | D7: SI | E7: NO | F7: 1.2 | G7: AWS|sa-east-1
A8: AWS | B8: eu-central-1 | C8: Frankfurt | D8: SI | E8: NO | F8: 1 | G8: AWS|eu-central-1
A9: AWS | B9: eu-central-2 | C9: Zurich | D9: NO | E9: NO | F9: 1.1 | G9: AWS|eu-central-2
A10: AWS | B10: eu-west-1 | C10: Ireland | D10: NO | E10: NO | F10: 1 | G10: AWS|eu-west-1
A11: AWS | B11: eu-west-2 | C11: London | D11: SI | E11: NO | F11: 1.1 | G11: AWS|eu-west-2
A12: AWS | B12: eu-west-3 | C12: Paris | D12: NO | E12: NO | F12: 1 | G12: AWS|eu-west-3
A13: AWS | B13: eu-north-1 | C13: Stockholm | D13: NO | E13: NO | F13: 1 | G13: AWS|eu-north-1
... A90: GCP | B90: me-central2 | C90: Dammam | D90: NO | E90: NO | F90: 1.2 | G90: GCP|me-central2

Sheet Listas
A1: Cloud | B1: Availability | C1: Direccion
A2: AWS | B2: Multi-zone | C2: Unidirectional
A3: Azure | B3: Single-zone | C3: Bidirectional
A4: GCP | C4: None

Sheet Consideraciones
A1: Consideraciones oficiales · Dedicated Private Link + Cluster Linking
A2: Fuente | B2: Regla | C2: Detalle
A3: Billing Dimensions | B3: Hourly público | C3: $0.25/h por cluster con internet endpoints. Ambos clusters pagan si ambos son Confluent Cloud.
A4: Billing Dimensions | B4: Hourly private intra-cloud | C4: $0.50/h por cluster privately networked. Bidirectional = 2 links al rate más alto ($0.50).
A5: Billing Dimensions | B5: Hourly cross-cloud private | C5: Aplica si (1) distinto cloud provider y (2) ambos usan private networking. $2.50/h por cluster, $5.00 si Premium region.
A6: Billing Dimensions | B6: ClusterLinkingWrite | C6: Mismo precio que KafkaNetworkWrite del destination. No se cobra Kafka ingress adicional.
A7: Billing Dimensions | B7: ClusterLinkingRead | C7: $0.25/GB incluyendo metadata. Confluent paga el egress del cloud provider. Hay volume discounts con account team.
A8: Billing Dimensions | B8: Se cobra el objeto | C8: Hay cargo aunque no exista mirror topic ni throughput. Confluent no de-duplica links idénticos.
A9: Billing Dimensions | B9: Regional multiplier | C9: Se aplica a precios base. Ejemplo docs: AWS us-east-1 = 1.0×, GCP asia-east2 = 1.2×. Los $2.50/$5.00 ya son el hourly cross-cloud; no se re-multiplica.
A10: Billing Dimensions | B10: Storage RF=3 | C10: Storage se factura post-replication. Dedicated replica 3 veces ≈ 3× el volumen escrito.
A11: Billing Dimensions | B11: GiB y UTC | C11: 1 GB = 2^30 bytes. Billing en UTC.
A12: Cluster Linking private | B12: Misma organization | C12: Dedicated/Enterprise private → private (mismo o distinto cloud) exige la misma Confluent Cloud Organization. Cross-org no soportado.
A13: Cluster Linking private | B13: Dedicated ↔ Dedicated private | C13: Soportado AWS↔Azure↔GCP. Source-initiated, destination-initiated o bidirectional.
... A28: PL Dedicated (los 3) | B28: Flink / SR | C28: El inbound PL de Dedicated también puede usarse para algunos productos serverless (Flink, Schema Registry) según docs de cada servicio.
