Workbook
Name RATE_ACTIONS: Tarifas!$B$4
Name RATE_ACTIVE: Tarifas!$B$5
Name RATE_RETAINED: Tarifas!$B$6
Name HORAS_MES: Tarifas!$B$7
Name ORIGENES: Listas!$A$2:$A$5
Name TIPOS: Listas!$B$2:$B$13
Name TIPO_UNIDAD: Listas!$B$2:$C$13
Name WF_NAMES: Workflows!$A$2:$A$21

Sheet Tarifas
A1: Temporal Cloud — tarifas commitment 3 años (celdas amarillas = input)
A3: Parámetro | B3: Valor | C3: Nota
A4: Actions ($ / millón) | B4: 23.16 | C4: Contrato. List público empieza en $50/millón.
A5: Active Storage ($ / GB-h) | B5: 0.039 | C5: Contrato. List público $0.042/GBh.
A6: Retained Storage ($ / GB-h) | B6: 0.00105 | C6: Igual al list público.
A7: Horas / mes (referencia GB) | B7: 730 | C7: Temporal usa 744 h para GB incluidos del plan. No entra en Actions.
A9: Cómo leer
A10: 1. Hoja Workflows: un type por fila (nombre, ejecuciones/mes, origen, duración open, KB de history, retention).
A11: 2. Hoja Pasos: detail de cada type. Veces × (% camino/100) × unidad oficial. Activity suma retries y heartbeats.
A12: 3. Hoja Resumen: totales del mes. Amarillo = input. Verde = fórmula. No editar verde.
A13: 4. Origen Cliente = 1 start_workflow. Signal-With-Start = 1. Schedule = 3 (incluye el start). Ninguno = 0.
A14: 5. Child (hijo NO listado) = 2 Actions. Si el hijo es otra fila en Workflows, no uses ese tipo en el padre.
A15: 6. Storage: 1 GB = 1.000.000 KB. Activo = exec × (KB/1e6) × horas open. Retenido = exec × GB × días × 24. Nombres de workflow unicos (SUMIF).
A16: 7. Replay no factura. Heartbeat solo si llega al server (SDK ~80% del Heartbeat Timeout).
A17: 8. Fuentes: https://docs.temporal.io/cloud/actions y https://docs.temporal.io/cloud/pricing

Sheet Resumen
A1: Resumen mensual — Temporal Cloud (commitment 3 años)
A3: Indicador | B3: Cantidad | C3: USD / mes
A4: Tipos de workflow con nombre | B4: =COUNTA(Workflows!A2:A21) | C4: -
A5: Ejecuciones / mes | B5: =SUMIF(Workflows!A2:A21,"<>",Workflows!B2:B21) | C5: -
A6: Actions / mes | B6: =SUMIF(Workflows!A2:A21,"<>",Workflows!I2:I21) | C6: =B6/1000000*RATE_ACTIONS
A7: Actions (millones) | B7: =B6/1000000 | C7: -
A8: Actions / ejecución (media) | B8: =IF(B5=0,0,B6/B5) | C8: -
A9: Active Storage (GBh) | B9: =SUMIF(Workflows!A2:A21,"<>",Workflows!J2:J21) | C9: =B9*RATE_ACTIVE
A10: Retained Storage (GBh) | B10: =SUMIF(Workflows!A2:A21,"<>",Workflows!K2:K21) | C10: =B10*RATE_RETAINED
A11: GB activo equivalente (GBh / horas mes) | B11: =IF(HORAS_MES=0,0,B9/HORAS_MES) | C11: -
A12: TOTAL USD / mes | B12: - | C12: =N(C6)+N(C9)+N(C10)
A13: Nombres duplicados en Workflows (0 = OK) | B13: =SUMPRODUCT((Workflows!A2:A21<>"")*(COUNTIF(Workflows!A2:A21,Workflows!A2:A21)>1)) | C13: -
A14: Costo por workflow type: columnas L-O de la hoja Workflows.
A16: Estimado de regimen, no la factura. Temporal documenta hasta 5% de diferencia entre metricas OpenMetrics y metering. No incluye Support, Export, Fairness ni TRU ociosos. Abrir en Excel para Windows o Microsoft 365: Habilitar edicion si aparece Vista protegida.

Sheet Listas
A1: Origen | B1: Tipo de paso | C1: Actions unitarias
A2: Cliente | B2: Activity | C2: 1
A3: Signal-With-Start | B3: Local Activities (1 por WFT) | C3: 1
A4: Schedule | B4: Timer / timeout SDK | C4: 1
A5: Ninguno | B5: Signal | C5: 1
B6: Signal externo | C6: 1
B7: Query | C7: 1
B8: Update | C8: 1
B9: Child (hijo NO listado) | C9: 2
B10: Continue-As-New | C10: 1
B11: Upsert Search Attributes | C11: 1
B12: Nexus Operation (caller) | C12: 1
B13: WFT Heartbeat (LA largas) | C13: 1

Sheet Workflows
A1: Nombre (type) | B1: Ejecuciones / mes | C1: Origen | D1: Actions origen | E1: Duración open (h) | F1: History promedio (KB) | G1: Retention (días) | H1: Actions/exec (pasos) | I1: Actions / mes | J1: Active GBh | K1: Retained GBh | L1: USD Actions | M1: USD Active | N1: USD Retained | O1: USD total
A2: Pago interbancario | B2: 50000 | C2: Cliente | D2: =IF(A2="","",IF(C2="Signal-With-Start",1,IF(C2="Schedule",3,IF(C2="Ninguno",0,1)))) | E2: 0.4 | F2: 80 | G2: 30 | H2: =IF(A2="","",SUMIF(Pasos!$A$2:$A$151,A2,Pasos!$I$2:$I$151)) | I2: =IF(A2="","",MAX(0,N(B2))*(D2+H2)) | J2: =IF(A2="","",MAX(0,N(B2))*(MAX(0,N(F2))/1000000)*MAX(0,N(E2))) | K2: =IF(A2="","",MAX(0,N(B2))*(MAX(0,N(F2))/1000000)*MAX(0,N(G2))*24) | L2: =IF(A2="","",I2/1000000*RATE_ACTIONS) | M2: =IF(A2="","",J2*RATE_ACTIVE) | N2: =IF(A2="","",K2*RATE_RETAINED) | O2: =IF(A2="","",L2+M2+N2)
A3: Alta de cliente | B3: 8000 | C3: Schedule | D3: =IF(A3="","",IF(C3="Signal-With-Start",1,IF(C3="Schedule",3,IF(C3="Ninguno",0,1)))) | E3: 2.5 | F3: 120 | G3: 30 | H3: =IF(A3="","",SUMIF(Pasos!$A$2:$A$151,A3,Pasos!$I$2:$I$151)) | I3: =IF(A3="","",MAX(0,N(B3))*(D3+H3)) | J3: =IF(A3="","",MAX(0,N(B3))*(MAX(0,N(F3))/1000000)*MAX(0,N(E3))) | K3: =IF(A3="","",MAX(0,N(B3))*(MAX(0,N(F3))/1000000)*MAX(0,N(G3))*24) | L3: =IF(A3="","",I3/1000000*RATE_ACTIONS) | M3: =IF(A3="","",J3*RATE_ACTIVE) | N3: =IF(A3="","",K3*RATE_RETAINED) | O3: =IF(A3="","",L3+M3+N3)
D4: =IF(A4="","",IF(C4="Signal-With-Start",1,IF(C4="Schedule",3,IF(C4="Ninguno",0,1)))) | H4: =IF(A4="","",SUMIF(Pasos!$A$2:$A$151,A4,Pasos!$I$2:$I$151)) | I4: =IF(A4="","",MAX(0,N(B4))*(D4+H4)) | J4: =IF(A4="","",MAX(0,N(B4))*(MAX(0,N(F4))/1000000)*MAX(0,N(E4))) | K4: =IF(A4="","",MAX(0,N(B4))*(MAX(0,N(F4))/1000000)*MAX(0,N(G4))*24) | L4: =IF(A4="","",I4/1000000*RATE_ACTIONS) | M4: =IF(A4="","",J4*RATE_ACTIVE) | N4: =IF(A4="","",K4*RATE_RETAINED) | O4: =IF(A4="","",L4+M4+N4)
D5: =IF(A5="","",IF(C5="Signal-With-Start",1,IF(C5="Schedule",3,IF(C5="Ninguno",0,1)))) | H5: =IF(A5="","",SUMIF(Pasos!$A$2:$A$151,A5,Pasos!$I$2:$I$151)) | I5: =IF(A5="","",MAX(0,N(B5))*(D5+H5)) | J5: =IF(A5="","",MAX(0,N(B5))*(MAX(0,N(F5))/1000000)*MAX(0,N(E5))) | K5: =IF(A5="","",MAX(0,N(B5))*(MAX(0,N(F5))/1000000)*MAX(0,N(G5))*24) | L5: =IF(A5="","",I5/1000000*RATE_ACTIONS) | M5: =IF(A5="","",J5*RATE_ACTIVE) | N5: =IF(A5="","",K5*RATE_RETAINED) | O5: =IF(A5="","",L5+M5+N5)
D6: =IF(A6="","",IF(C6="Signal-With-Start",1,IF(C6="Schedule",3,IF(C6="Ninguno",0,1)))) | H6: =IF(A6="","",SUMIF(Pasos!$A$2:$A$151,A6,Pasos!$I$2:$I$151)) | I6: =IF(A6="","",MAX(0,N(B6))*(D6+H6)) | J6: =IF(A6="","",MAX(0,N(B6))*(MAX(0,N(F6))/1000000)*MAX(0,N(E6))) | K6: =IF(A6="","",MAX(0,N(B6))*(MAX(0,N(F6))/1000000)*MAX(0,N(G6))*24) | L6: =IF(A6="","",I6/1000000*RATE_ACTIONS) | M6: =IF(A6="","",J6*RATE_ACTIVE) | N6: =IF(A6="","",K6*RATE_RETAINED) | O6: =IF(A6="","",L6+M6+N6)
D7: =IF(A7="","",IF(C7="Signal-With-Start",1,IF(C7="Schedule",3,IF(C7="Ninguno",0,1)))) | H7: =IF(A7="","",SUMIF(Pasos!$A$2:$A$151,A7,Pasos!$I$2:$I$151)) | I7: =IF(A7="","",MAX(0,N(B7))*(D7+H7)) | J7: =IF(A7="","",MAX(0,N(B7))*(MAX(0,N(F7))/1000000)*MAX(0,N(E7))) | K7: =IF(A7="","",MAX(0,N(B7))*(MAX(0,N(F7))/1000000)*MAX(0,N(G7))*24) | L7: =IF(A7="","",I7/1000000*RATE_ACTIONS) | M7: =IF(A7="","",J7*RATE_ACTIVE) | N7: =IF(A7="","",K7*RATE_RETAINED) | O7: =IF(A7="","",L7+M7+N7)
D8: =IF(A8="","",IF(C8="Signal-With-Start",1,IF(C8="Schedule",3,IF(C8="Ninguno",0,1)))) | H8: =IF(A8="","",SUMIF(Pasos!$A$2:$A$151,A8,Pasos!$I$2:$I$151)) | I8: =IF(A8="","",MAX(0,N(B8))*(D8+H8)) | J8: =IF(A8="","",MAX(0,N(B8))*(MAX(0,N(F8))/1000000)*MAX(0,N(E8))) | K8: =IF(A8="","",MAX(0,N(B8))*(MAX(0,N(F8))/1000000)*MAX(0,N(G8))*24) | L8: =IF(A8="","",I8/1000000*RATE_ACTIONS) | M8: =IF(A8="","",J8*RATE_ACTIVE) | N8: =IF(A8="","",K8*RATE_RETAINED) | O8: =IF(A8="","",L8+M8+N8)
D9: =IF(A9="","",IF(C9="Signal-With-Start",1,IF(C9="Schedule",3,IF(C9="Ninguno",0,1)))) | H9: =IF(A9="","",SUMIF(Pasos!$A$2:$A$151,A9,Pasos!$I$2:$I$151)) | I9: =IF(A9="","",MAX(0,N(B9))*(D9+H9)) | J9: =IF(A9="","",MAX(0,N(B9))*(MAX(0,N(F9))/1000000)*MAX(0,N(E9))) | K9: =IF(A9="","",MAX(0,N(B9))*(MAX(0,N(F9))/1000000)*MAX(0,N(G9))*24) | L9: =IF(A9="","",I9/1000000*RATE_ACTIONS) | M9: =IF(A9="","",J9*RATE_ACTIVE) | N9: =IF(A9="","",K9*RATE_RETAINED) | O9: =IF(A9="","",L9+M9+N9)
D10: =IF(A10="","",IF(C10="Signal-With-Start",1,IF(C10="Schedule",3,IF(C10="Ninguno",0,1)))) | H10: =IF(A10="","",SUMIF(Pasos!$A$2:$A$151,A10,Pasos!$I$2:$I$151)) | I10: =IF(A10="","",MAX(0,N(B10))*(D10+H10)) | J10: =IF(A10="","",MAX(0,N(B10))*(MAX(0,N(F10))/1000000)*MAX(0,N(E10))) | K10: =IF(A10="","",MAX(0,N(B10))*(MAX(0,N(F10))/1000000)*MAX(0,N(G10))*24) | L10: =IF(A10="","",I10/1000000*RATE_ACTIONS) | M10: =IF(A10="","",J10*RATE_ACTIVE) | N10: =IF(A10="","",K10*RATE_RETAINED) | O10: =IF(A10="","",L10+M10+N10)
D11: =IF(A11="","",IF(C11="Signal-With-Start",1,IF(C11="Schedule",3,IF(C11="Ninguno",0,1)))) | H11: =IF(A11="","",SUMIF(Pasos!$A$2:$A$151,A11,Pasos!$I$2:$I$151)) | I11: =IF(A11="","",MAX(0,N(B11))*(D11+H11)) | J11: =IF(A11="","",MAX(0,N(B11))*(MAX(0,N(F11))/1000000)*MAX(0,N(E11))) | K11: =IF(A11="","",MAX(0,N(B11))*(MAX(0,N(F11))/1000000)*MAX(0,N(G11))*24) | L11: =IF(A11="","",I11/1000000*RATE_ACTIONS) | M11: =IF(A11="","",J11*RATE_ACTIVE) | N11: =IF(A11="","",K11*RATE_RETAINED) | O11: =IF(A11="","",L11+M11+N11)
D12: =IF(A12="","",IF(C12="Signal-With-Start",1,IF(C12="Schedule",3,IF(C12="Ninguno",0,1)))) | H12: =IF(A12="","",SUMIF(Pasos!$A$2:$A$151,A12,Pasos!$I$2:$I$151)) | I12: =IF(A12="","",MAX(0,N(B12))*(D12+H12)) | J12: =IF(A12="","",MAX(0,N(B12))*(MAX(0,N(F12))/1000000)*MAX(0,N(E12))) | K12: =IF(A12="","",MAX(0,N(B12))*(MAX(0,N(F12))/1000000)*MAX(0,N(G12))*24) | L12: =IF(A12="","",I12/1000000*RATE_ACTIONS) | M12: =IF(A12="","",J12*RATE_ACTIVE) | N12: =IF(A12="","",K12*RATE_RETAINED) | O12: =IF(A12="","",L12+M12+N12)
D13: =IF(A13="","",IF(C13="Signal-With-Start",1,IF(C13="Schedule",3,IF(C13="Ninguno",0,1)))) | H13: =IF(A13="","",SUMIF(Pasos!$A$2:$A$151,A13,Pasos!$I$2:$I$151)) | I13: =IF(A13="","",MAX(0,N(B13))*(D13+H13)) | J13: =IF(A13="","",MAX(0,N(B13))*(MAX(0,N(F13))/1000000)*MAX(0,N(E13))) | K13: =IF(A13="","",MAX(0,N(B13))*(MAX(0,N(F13))/1000000)*MAX(0,N(G13))*24) | L13: =IF(A13="","",I13/1000000*RATE_ACTIONS) | M13: =IF(A13="","",J13*RATE_ACTIVE) | N13: =IF(A13="","",K13*RATE_RETAINED) | O13: =IF(A13="","",L13+M13+N13)
D14: =IF(A14="","",IF(C14="Signal-With-Start",1,IF(C14="Schedule",3,IF(C14="Ninguno",0,1)))) | H14: =IF(A14="","",SUMIF(Pasos!$A$2:$A$151,A14,Pasos!$I$2:$I$151)) | I14: =IF(A14="","",MAX(0,N(B14))*(D14+H14)) | J14: =IF(A14="","",MAX(0,N(B14))*(MAX(0,N(F14))/1000000)*MAX(0,N(E14))) | K14: =IF(A14="","",MAX(0,N(B14))*(MAX(0,N(F14))/1000000)*MAX(0,N(G14))*24) | L14: =IF(A14="","",I14/1000000*RATE_ACTIONS) | M14: =IF(A14="","",J14*RATE_ACTIVE) | N14: =IF(A14="","",K14*RATE_RETAINED) | O14: =IF(A14="","",L14+M14+N14)
D15: =IF(A15="","",IF(C15="Signal-With-Start",1,IF(C15="Schedule",3,IF(C15="Ninguno",0,1)))) | H15: =IF(A15="","",SUMIF(Pasos!$A$2:$A$151,A15,Pasos!$I$2:$I$151)) | I15: =IF(A15="","",MAX(0,N(B15))*(D15+H15)) | J15: =IF(A15="","",MAX(0,N(B15))*(MAX(0,N(F15))/1000000)*MAX(0,N(E15))) | K15: =IF(A15="","",MAX(0,N(B15))*(MAX(0,N(F15))/1000000)*MAX(0,N(G15))*24) | L15: =IF(A15="","",I15/1000000*RATE_ACTIONS) | M15: =IF(A15="","",J15*RATE_ACTIVE) | N15: =IF(A15="","",K15*RATE_RETAINED) | O15: =IF(A15="","",L15+M15+N15)
... D21: =IF(A21="","",IF(C21="Signal-With-Start",1,IF(C21="Schedule",3,IF(C21="Ninguno",0,1)))) | H21: =IF(A21="","",SUMIF(Pasos!$A$2:$A$151,A21,Pasos!$I$2:$I$151)) | I21: =IF(A21="","",MAX(0,N(B21))*(D21+H21)) | J21: =IF(A21="","",MAX(0,N(B21))*(MAX(0,N(F21))/1000000)*MAX(0,N(E21))) | K21: =IF(A21="","",MAX(0,N(B21))*(MAX(0,N(F21))/1000000)*MAX(0,N(G21))*24) | L21: =IF(A21="","",I21/1000000*RATE_ACTIONS) | M21: =IF(A21="","",J21*RATE_ACTIVE) | N21: =IF(A21="","",K21*RATE_RETAINED) | O21: =IF(A21="","",L21+M21+N21)

Sheet Pasos
A1: Workflow (type) | B1: Tipo de paso | C1: Nombre del paso | D1: Veces si el camino ocurre | E1: % del flujo | F1: Retries avg (solo Activity) | G1: Heartbeats avg (solo Activity) | H1: Unidad oficial | I1: Actions / ejecución
A2: Pago interbancario | B2: Activity | C2: Validar cuenta | D2: 1 | E2: 100 | F2: 0 | G2: 0 | H2: =IF(B2="","",IFERROR(VLOOKUP(B2,Listas!$B$2:$C$13,2,0),1)) | I2: =IF(OR(A2="",B2=""),"",IF(B2="Activity",MAX(0,N(D2))*(MIN(100,MAX(0,N(E2)))/100)*(1+MAX(0,N(F2))+MAX(0,N(G2))),MAX(0,N(D2))*(MIN(100,MAX(0,N(E2)))/100)*H2))
A3: Pago interbancario | B3: Activity | C3: Débito core | D3: 1 | E3: 98 | F3: 0.3 | G3: 4 | H3: =IF(B3="","",IFERROR(VLOOKUP(B3,Listas!$B$2:$C$13,2,0),1)) | I3: =IF(OR(A3="",B3=""),"",IF(B3="Activity",MAX(0,N(D3))*(MIN(100,MAX(0,N(E3)))/100)*(1+MAX(0,N(F3))+MAX(0,N(G3))),MAX(0,N(D3))*(MIN(100,MAX(0,N(E3)))/100)*H3))
A4: Pago interbancario | B4: Activity | C4: Crédito destino | D4: 1 | E4: 95 | F4: 0.4 | G4: 6 | H4: =IF(B4="","",IFERROR(VLOOKUP(B4,Listas!$B$2:$C$13,2,0),1)) | I4: =IF(OR(A4="",B4=""),"",IF(B4="Activity",MAX(0,N(D4))*(MIN(100,MAX(0,N(E4)))/100)*(1+MAX(0,N(F4))+MAX(0,N(G4))),MAX(0,N(D4))*(MIN(100,MAX(0,N(E4)))/100)*H4))
A5: Pago interbancario | B5: Activity | C5: Notificar | D5: 1 | E5: 100 | F5: 0 | G5: 0 | H5: =IF(B5="","",IFERROR(VLOOKUP(B5,Listas!$B$2:$C$13,2,0),1)) | I5: =IF(OR(A5="",B5=""),"",IF(B5="Activity",MAX(0,N(D5))*(MIN(100,MAX(0,N(E5)))/100)*(1+MAX(0,N(F5))+MAX(0,N(G5))),MAX(0,N(D5))*(MIN(100,MAX(0,N(E5)))/100)*H5))
A6: Pago interbancario | B6: Timer / timeout SDK | C6: Espera SLA / AwaitWithTimeout | D6: 1 | E6: 15 | F6: 0 | G6: 0 | H6: =IF(B6="","",IFERROR(VLOOKUP(B6,Listas!$B$2:$C$13,2,0),1)) | I6: =IF(OR(A6="",B6=""),"",IF(B6="Activity",MAX(0,N(D6))*(MIN(100,MAX(0,N(E6)))/100)*(1+MAX(0,N(F6))+MAX(0,N(G6))),MAX(0,N(D6))*(MIN(100,MAX(0,N(E6)))/100)*H6))
A7: Pago interbancario | B7: Signal | C7: Confirmación manual | D7: 1 | E7: 8 | F7: 0 | G7: 0 | H7: =IF(B7="","",IFERROR(VLOOKUP(B7,Listas!$B$2:$C$13,2,0),1)) | I7: =IF(OR(A7="",B7=""),"",IF(B7="Activity",MAX(0,N(D7))*(MIN(100,MAX(0,N(E7)))/100)*(1+MAX(0,N(F7))+MAX(0,N(G7))),MAX(0,N(D7))*(MIN(100,MAX(0,N(E7)))/100)*H7))
A8: Pago interbancario | B8: Query | C8: Consulta estado UI | D8: 2 | E8: 40 | F8: 0 | G8: 0 | H8: =IF(B8="","",IFERROR(VLOOKUP(B8,Listas!$B$2:$C$13,2,0),1)) | I8: =IF(OR(A8="",B8=""),"",IF(B8="Activity",MAX(0,N(D8))*(MIN(100,MAX(0,N(E8)))/100)*(1+MAX(0,N(F8))+MAX(0,N(G8))),MAX(0,N(D8))*(MIN(100,MAX(0,N(E8)))/100)*H8))
A9: Alta de cliente | B9: Activity | C9: KYC | D9: 1 | E9: 100 | F9: 1 | G9: 12 | H9: =IF(B9="","",IFERROR(VLOOKUP(B9,Listas!$B$2:$C$13,2,0),1)) | I9: =IF(OR(A9="",B9=""),"",IF(B9="Activity",MAX(0,N(D9))*(MIN(100,MAX(0,N(E9)))/100)*(1+MAX(0,N(F9))+MAX(0,N(G9))),MAX(0,N(D9))*(MIN(100,MAX(0,N(E9)))/100)*H9))
A10: Alta de cliente | B10: Activity | C10: Crear producto | D10: 1 | E10: 85 | F10: 0.2 | G10: 2 | H10: =IF(B10="","",IFERROR(VLOOKUP(B10,Listas!$B$2:$C$13,2,0),1)) | I10: =IF(OR(A10="",B10=""),"",IF(B10="Activity",MAX(0,N(D10))*(MIN(100,MAX(0,N(E10)))/100)*(1+MAX(0,N(F10))+MAX(0,N(G10))),MAX(0,N(D10))*(MIN(100,MAX(0,N(E10)))/100)*H10))
A11: Alta de cliente | B11: Timer / timeout SDK | C11: Espera documentos | D11: 1 | E11: 30 | F11: 0 | G11: 0 | H11: =IF(B11="","",IFERROR(VLOOKUP(B11,Listas!$B$2:$C$13,2,0),1)) | I11: =IF(OR(A11="",B11=""),"",IF(B11="Activity",MAX(0,N(D11))*(MIN(100,MAX(0,N(E11)))/100)*(1+MAX(0,N(F11))+MAX(0,N(G11))),MAX(0,N(D11))*(MIN(100,MAX(0,N(E11)))/100)*H11))
A12: Alta de cliente | B12: Signal | C12: Documentos listos | D12: 1 | E12: 30 | F12: 0 | G12: 0 | H12: =IF(B12="","",IFERROR(VLOOKUP(B12,Listas!$B$2:$C$13,2,0),1)) | I12: =IF(OR(A12="",B12=""),"",IF(B12="Activity",MAX(0,N(D12))*(MIN(100,MAX(0,N(E12)))/100)*(1+MAX(0,N(F12))+MAX(0,N(G12))),MAX(0,N(D12))*(MIN(100,MAX(0,N(E12)))/100)*H12))
A13: Alta de cliente | B13: Child (hijo NO listado) | C13: Onboarding cards (no listado) | D13: 1 | E13: 60 | F13: 0 | G13: 0 | H13: =IF(B13="","",IFERROR(VLOOKUP(B13,Listas!$B$2:$C$13,2,0),1)) | I13: =IF(OR(A13="",B13=""),"",IF(B13="Activity",MAX(0,N(D13))*(MIN(100,MAX(0,N(E13)))/100)*(1+MAX(0,N(F13))+MAX(0,N(G13))),MAX(0,N(D13))*(MIN(100,MAX(0,N(E13)))/100)*H13))
H14: =IF(B14="","",IFERROR(VLOOKUP(B14,Listas!$B$2:$C$13,2,0),1)) | I14: =IF(OR(A14="",B14=""),"",IF(B14="Activity",MAX(0,N(D14))*(MIN(100,MAX(0,N(E14)))/100)*(1+MAX(0,N(F14))+MAX(0,N(G14))),MAX(0,N(D14))*(MIN(100,MAX(0,N(E14)))/100)*H14))
H15: =IF(B15="","",IFERROR(VLOOKUP(B15,Listas!$B$2:$C$13,2,0),1)) | I15: =IF(OR(A15="",B15=""),"",IF(B15="Activity",MAX(0,N(D15))*(MIN(100,MAX(0,N(E15)))/100)*(1+MAX(0,N(F15))+MAX(0,N(G15))),MAX(0,N(D15))*(MIN(100,MAX(0,N(E15)))/100)*H15))
H16: =IF(B16="","",IFERROR(VLOOKUP(B16,Listas!$B$2:$C$13,2,0),1)) | I16: =IF(OR(A16="",B16=""),"",IF(B16="Activity",MAX(0,N(D16))*(MIN(100,MAX(0,N(E16)))/100)*(1+MAX(0,N(F16))+MAX(0,N(G16))),MAX(0,N(D16))*(MIN(100,MAX(0,N(E16)))/100)*H16))
H17: =IF(B17="","",IFERROR(VLOOKUP(B17,Listas!$B$2:$C$13,2,0),1)) | I17: =IF(OR(A17="",B17=""),"",IF(B17="Activity",MAX(0,N(D17))*(MIN(100,MAX(0,N(E17)))/100)*(1+MAX(0,N(F17))+MAX(0,N(G17))),MAX(0,N(D17))*(MIN(100,MAX(0,N(E17)))/100)*H17))
H18: =IF(B18="","",IFERROR(VLOOKUP(B18,Listas!$B$2:$C$13,2,0),1)) | I18: =IF(OR(A18="",B18=""),"",IF(B18="Activity",MAX(0,N(D18))*(MIN(100,MAX(0,N(E18)))/100)*(1+MAX(0,N(F18))+MAX(0,N(G18))),MAX(0,N(D18))*(MIN(100,MAX(0,N(E18)))/100)*H18))
H19: =IF(B19="","",IFERROR(VLOOKUP(B19,Listas!$B$2:$C$13,2,0),1)) | I19: =IF(OR(A19="",B19=""),"",IF(B19="Activity",MAX(0,N(D19))*(MIN(100,MAX(0,N(E19)))/100)*(1+MAX(0,N(F19))+MAX(0,N(G19))),MAX(0,N(D19))*(MIN(100,MAX(0,N(E19)))/100)*H19))
H20: =IF(B20="","",IFERROR(VLOOKUP(B20,Listas!$B$2:$C$13,2,0),1)) | I20: =IF(OR(A20="",B20=""),"",IF(B20="Activity",MAX(0,N(D20))*(MIN(100,MAX(0,N(E20)))/100)*(1+MAX(0,N(F20))+MAX(0,N(G20))),MAX(0,N(D20))*(MIN(100,MAX(0,N(E20)))/100)*H20))
H21: =IF(B21="","",IFERROR(VLOOKUP(B21,Listas!$B$2:$C$13,2,0),1)) | I21: =IF(OR(A21="",B21=""),"",IF(B21="Activity",MAX(0,N(D21))*(MIN(100,MAX(0,N(E21)))/100)*(1+MAX(0,N(F21))+MAX(0,N(G21))),MAX(0,N(D21))*(MIN(100,MAX(0,N(E21)))/100)*H21))
H22: =IF(B22="","",IFERROR(VLOOKUP(B22,Listas!$B$2:$C$13,2,0),1)) | I22: =IF(OR(A22="",B22=""),"",IF(B22="Activity",MAX(0,N(D22))*(MIN(100,MAX(0,N(E22)))/100)*(1+MAX(0,N(F22))+MAX(0,N(G22))),MAX(0,N(D22))*(MIN(100,MAX(0,N(E22)))/100)*H22))
H23: =IF(B23="","",IFERROR(VLOOKUP(B23,Listas!$B$2:$C$13,2,0),1)) | I23: =IF(OR(A23="",B23=""),"",IF(B23="Activity",MAX(0,N(D23))*(MIN(100,MAX(0,N(E23)))/100)*(1+MAX(0,N(F23))+MAX(0,N(G23))),MAX(0,N(D23))*(MIN(100,MAX(0,N(E23)))/100)*H23))
H24: =IF(B24="","",IFERROR(VLOOKUP(B24,Listas!$B$2:$C$13,2,0),1)) | I24: =IF(OR(A24="",B24=""),"",IF(B24="Activity",MAX(0,N(D24))*(MIN(100,MAX(0,N(E24)))/100)*(1+MAX(0,N(F24))+MAX(0,N(G24))),MAX(0,N(D24))*(MIN(100,MAX(0,N(E24)))/100)*H24))
H25: =IF(B25="","",IFERROR(VLOOKUP(B25,Listas!$B$2:$C$13,2,0),1)) | I25: =IF(OR(A25="",B25=""),"",IF(B25="Activity",MAX(0,N(D25))*(MIN(100,MAX(0,N(E25)))/100)*(1+MAX(0,N(F25))+MAX(0,N(G25))),MAX(0,N(D25))*(MIN(100,MAX(0,N(E25)))/100)*H25))
... H151: =IF(B151="","",IFERROR(VLOOKUP(B151,Listas!$B$2:$C$13,2,0),1)) | I151: =IF(OR(A151="",B151=""),"",IF(B151="Activity",MAX(0,N(D151))*(MIN(100,MAX(0,N(E151)))/100)*(1+MAX(0,N(F151))+MAX(0,N(G151))),MAX(0,N(D151))*(MIN(100,MAX(0,N(E151)))/100)*H151))

Sheet Catalogo
A1: Catálogo oficial de Actions (referencia, no input)
A3: En la calculadora | B3: Usage / metric name | C3: Actions | D3: Nota oficial
A4: Origen Cliente | B4: start_workflow | C4: 1 | D4: Start vía client. Dedup por Workflow ID no cuenta.
A5: Origen Signal-With-Start | B5: signal_workflow_with_start | C5: 1 | D5: Un Action total, arranque o no.
A6: Origen Schedule | B6: schedule start + start_workflow | C6: 3 | D6: Schedule Start cuenta 2; el workflow 1.
A7: Activity | B7: schedule_activity + retry_activity + record_activity_heartbeat | C7: 1 + retries + HB | D7: HB solo si llega al server. SDK throttle ~80% del timeout.
A8: Local Activities (1 por WFT) | B8: record_activity_markers | C8: 1 por Workflow Task | D8: N Local Activities del mismo WFT = 1 Action.
A9: Timer / timeout SDK | B9: start_timer | C9: 1 | D9: Incluye AwaitWithTimeout / condition.
A10: Signal | B10: signal_workflow | C10: 1 | D10: Client o workflow.
A11: Signal externo | B11: signal_external_workflow | C11: 1 | D11: En el history del signaled.
A12: Query | B12: query_workflow | C12: 1 | D12: Incluye call stack en UI Cloud. __temporal_workflow_metadata excluida.
A13: Update | B13: accept_workflow_update / reject_workflow_update | C13: 1 | D13: Dedup por Update ID no cuenta.
A14: Child (hijo NO listado) | B14: start_child_workflow + start | C14: 2 | D14: Intent + intento de start. Si el hijo es otra fila, no uses este tipo.
... A19: Replay | B19: - | C19: 0 | D19: No factura. Solo worker.
A21: https://docs.temporal.io/cloud/actions
A22: https://docs.temporal.io/cloud/pricing
